arkitwist/__init__.py
arkitwist/attn.py
arkitwist/blocks.py
arkitwist-1.0.0.dist-info/LICENSE
arkitwist-1.0.0.dist-info/METADATA
arkitwist-1.0.0.dist-info/WHEEL
arkitwist-1.0.0.dist-info/top_level.txt
arkitwist-1.0.0.dist-info/RECORD
