Metadata-Version: 2.1
Name: arkitwist
Version: 1.0.0
Summary: Arkitwist: an variant of reformer
Author: Project VsingerXiaoice Consensus
Author-email: alan_sudo@yeah.net
License: The Unlicense
Requires: torch
License-File: LICENSE
